MANIFEST.in
README.txt
html.py
setup.py
html.egg-info/PKG-INFO
html.egg-info/SOURCES.txt
html.egg-info/dependency_links.txt
html.egg-info/top_level.txt